deephaven_ipywidgets/__init__.py
deephaven_ipywidgets/_frontend.py
deephaven_ipywidgets/_version.py
deephaven_ipywidgets/deephaven.py
deephaven_ipywidgets/labextension/package.json
deephaven_ipywidgets/labextension/static/367.71bb4ea708f764560134.js
deephaven_ipywidgets/labextension/static/480.d328a2918d5d3224b5e9.js
deephaven_ipywidgets/labextension/static/568.824bfc30086125cbc840.js
deephaven_ipywidgets/labextension/static/701.33288d25ebc978bba3f2.js
deephaven_ipywidgets/labextension/static/783.950f52d78c9ac67aa7aa.js
deephaven_ipywidgets/labextension/static/remoteEntry.692062e4c090fb1084ff.js
deephaven_ipywidgets/labextension/static/style.js
deephaven_ipywidgets/labextension/static/third-party-licenses.json
deephaven_ipywidgets/nbextension/extension.js
deephaven_ipywidgets/nbextension/index.js
deephaven_ipywidgets/nbextension/index.js.map
deephaven_ipywidgets/tests/__init__.py
deephaven_ipywidgets/tests/conftest.py
deephaven_ipywidgets/tests/test_nbextension_path.py
deephaven_ipywidgets/tests/test_table.py
deephaven_ipywidgets-0.6.2.data/data/etc/jupyter/nbconfig/notebook.d/deephaven_ipywidgets.json
deephaven_ipywidgets-0.6.2.data/data/share/jupyter/labextensions/@deephaven/ipywidgets/install.json
deephaven_ipywidgets-0.6.2.data/data/share/jupyter/labextensions/@deephaven/ipywidgets/package.json
deephaven_ipywidgets-0.6.2.data/data/share/jupyter/labextensions/@deephaven/ipywidgets/static/367.71bb4ea708f764560134.js
deephaven_ipywidgets-0.6.2.data/data/share/jupyter/labextensions/@deephaven/ipywidgets/static/480.d328a2918d5d3224b5e9.js
deephaven_ipywidgets-0.6.2.data/data/share/jupyter/labextensions/@deephaven/ipywidgets/static/568.824bfc30086125cbc840.js
deephaven_ipywidgets-0.6.2.data/data/share/jupyter/labextensions/@deephaven/ipywidgets/static/701.33288d25ebc978bba3f2.js
deephaven_ipywidgets-0.6.2.data/data/share/jupyter/labextensions/@deephaven/ipywidgets/static/783.950f52d78c9ac67aa7aa.js
deephaven_ipywidgets-0.6.2.dist-info/LICENSE.txt
deephaven_ipywidgets-0.6.2.dist-info/METADATA
deephaven_ipywidgets-0.6.2.dist-info/WHEEL
deephaven_ipywidgets-0.6.2.dist-info/top_level.txt
deephaven_ipywidgets-0.6.2.dist-info/RECORD
