Metadata-Version: 2.1
Name: deephaven_ipywidgets
Version: 0.6.2
Summary: A Custom Jupyter Widget Library
Home-page: https://github.com/deephaven/deephaven-ipywidgets
Author: Deephaven Data Labs LLC
Author-email: operations@deephaven.io
License: BSD
Keywords: Jupyter,Widgets,IPython
Platform: Linux
Platform: Mac OS X
Platform: Windows
Classifier: Intended Audience :: Developers
Classifier: Intended Audience :: Science/Research
Classifier: License :: OSI Approved :: BSD License
Classifier: Programming Language :: Python
Classifier: Programming Language :: Python :: 3
Classifier: Programming Language :: Python :: 3.4
Classifier: Programming Language :: Python :: 3.5
Classifier: Programming Language :: Python :: 3.6
Classifier: Programming Language :: Python :: 3.7
Classifier: Framework :: Jupyter
Requires-Python: >=3.6
License-File: LICENSE.txt
Requires-Dist: ipywidgets <9,>=8.0.0
Provides-Extra: client
Requires-Dist: pydeephaven ; extra == 'client'
Provides-Extra: docs
Requires-Dist: jupyter-sphinx ; extra == 'docs'
Requires-Dist: nbsphinx ; extra == 'docs'
Requires-Dist: nbsphinx-link ; extra == 'docs'
Requires-Dist: pytest-check-links ; extra == 'docs'
Requires-Dist: pypandoc ; extra == 'docs'
Requires-Dist: recommonmark ; extra == 'docs'
Requires-Dist: sphinx >=1.5 ; extra == 'docs'
Requires-Dist: sphinx-rtd-theme ; extra == 'docs'
Provides-Extra: examples
Requires-Dist: deephaven-server >=0.31.0 ; extra == 'examples'
Requires-Dist: pydeephaven ; extra == 'examples'
Provides-Extra: server
Requires-Dist: deephaven-server >=0.31.0 ; extra == 'server'
Provides-Extra: test
Requires-Dist: pytest >=4.6 ; extra == 'test'
Requires-Dist: pytest-cov ; extra == 'test'
Requires-Dist: nbval ; extra == 'test'
